setup.py
pytickets.egg-info/PKG-INFO
pytickets.egg-info/SOURCES.txt
pytickets.egg-info/dependency_links.txt
pytickets.egg-info/top_level.txt
tickets/__init__.py
tickets/bytemapper.py
tickets/core.py
tickets/flags.py
tickets/log.py
tickets/types.py
tickets/crypto/__init__.py
tickets/crypto/aes.py
tickets/crypto/diffiehellman.py
tickets/crypto/rfc3526.py
tickets/crypto/util.py
tickets/tests/__init__.py
tickets/tests/__main__.py
tickets/tests/test_core.py
tickets/tests/test_web_forms.py
tickets/tests/utils.py
tickets/web/__init__.py
tickets/web/forms.py