Metadata-Version: 1.0
Name: pytickets
Version: 0.9.2.1
Summary: pyTickets are light-weight symmetrically signed data containers with optional encryption, serialization and compression of their contents. Now includes an *alpha* DiffieHellman implementation. Do not trust it yet :-)
Home-page: http://tripleaes.com/wp/pytickets
Author: Krister Hedfors
Author-email: krister@tripleaes.com
License: GPL
Keywords: ticket tickets encrypt secure sign signed ignature hash hashed
Platform: UNKNOWN
Classifier: Intended Audience :: Developers
Classifier: Development Status :: 4 - Beta
Classifier: License :: OSI Approved :: GNU General Public License (GPL)
Classifier: Programming Language :: Python
Classifier: Topic :: Security :: Cryptography
